pandera_tool/__init__.py
pandera_tool-0.1.0.dist-info/LICENSE
pandera_tool-0.1.0.dist-info/WHEEL
pandera_tool-0.1.0.dist-info/METADATA
pandera_tool-0.1.0.dist-info/RECORD
