Metadata-Version: 2.1
Name: pandera-tool
Version: 0.1.0
Summary: Tool for pandera.
Home-page: https://github.com/SaitoTsutomu/pandera-tool
License: Apache-2.0
Author: Saito Tsutomu
Author-email: tsutomu7@hotmail.co.jp
Requires-Python: >=3.10,<4.0
Classifier: Development Status :: 1 - Planning
Classifier: License :: OSI Approved :: Apache Software License
Classifier: Programming Language :: Python
Classifier: Programming Language :: Python :: 3
Classifier: Programming Language :: Python :: 3.10
Classifier: Topic :: Scientific/Engineering
Classifier: Topic :: Software Development
Requires-Dist: pandera (>=0.12,<0.13)
